moonshine/__init__.py
moonshine/moonshine.py
magic_moonshine-1.2.8.dist-info/METADATA
magic_moonshine-1.2.8.dist-info/WHEEL
magic_moonshine-1.2.8.dist-info/top_level.txt
magic_moonshine-1.2.8.dist-info/RECORD
