Metadata-Version: 2.4
Name: magic-moonshine
Version: 1.2.8
Summary: A powerful text-based video editing tool
Author-email: Moonshine <python@usemoonshine.com>
License: MIT
Requires-Dist: setuptools>=61.0
Requires-Dist: wheel
